Chips.py
Chips_CNC_Toolmanager-0.1.a1.dist-info/DESCRIPTION.rst
Chips_CNC_Toolmanager-0.1.a1.dist-info/LICENSE.txt
Chips_CNC_Toolmanager-0.1.a1.dist-info/METADATA
Chips_CNC_Toolmanager-0.1.a1.dist-info/RECORD
Chips_CNC_Toolmanager-0.1.a1.dist-info/WHEEL
Chips_CNC_Toolmanager-0.1.a1.dist-info/entry_points.txt
Chips_CNC_Toolmanager-0.1.a1.dist-info/metadata.json
Chips_CNC_Toolmanager-0.1.a1.dist-info/top_level.txt
chips/__init__.py
chips/actions.py
chips/application_admin.py
chips/calculations.py
chips/fixtures.py
chips/model.py
chips/processors.py
chips/test.py
chips/unicodeCSV.py
chips/utils.py
chips/validators.py
chips/art/__init__.py
chips/default_gcodes/__init__.py
chips/default_gcodes/cut.nc
chips/default_gcodes/machine_post.nc
chips/default_gcodes/machine_pre.nc
chips/default_gcodes/post_cut.nc
chips/default_gcodes/pre_cut.nc
