Metadata-Version: 2.0
Name: Chips-CNC-Toolmanager
Version: 0.1.a1
Summary: CNC tool test and management suite
Home-page: https://bitbucket.org/sebste/chips
Author: Sebastian Stetter
Author-email: sebastian.stetter@gmail.com
License: GPL License v2
Keywords: machining,CNC,tools,CAM,g-code,workshop
Platform: UNKNOWN
Classifier: Development Status :: 3 - Alpha
Classifier: Intended Audience :: End Users/Desktop
Classifier: Natural Language :: English
Classifier: License :: OSI Approved :: GNU General Public License v2 (GPLv2)
Classifier: Operating System :: OS Independent
Classifier: Environment :: X11 Applications
Classifier: Environment :: X11 Applications :: Qt
Classifier: Environment :: Win32 (MS Windows)
Classifier: Environment :: MacOS X
Classifier: Programming Language :: Python
Classifier: Programming Language :: Python :: 2
Classifier: Programming Language :: Python :: 2.6
Classifier: Programming Language :: Python :: 2.7
Classifier: Programming Language :: Python :: Implementation :: CPython
Classifier: Programming Language :: Python :: Implementation :: PyPy
Classifier: Topic :: Other/Nonlisted Topic
Requires-Dist: camelot (==13.04.13-gpl-pyqt)
